flowprep_ml/__init__.py
flowprep_ml/core.py
flowprep_ml/exceptions.py
flowprep_ml/options.py
flowprep_ml/utils.py
flowprep_ml-1.0.0.dist-info/licenses/LICENSE
flowprep_ml-1.0.0.dist-info/METADATA
flowprep_ml-1.0.0.dist-info/WHEEL
flowprep_ml-1.0.0.dist-info/top_level.txt
flowprep_ml-1.0.0.dist-info/RECORD
