Metadata-Version: 2.4
Name: flowprep-ml
Version: 1.0.0
Summary: Intelligent data preprocessing library with advanced options
Home-page: https://github.com/flowml/flowprep-ml
Author: Flow ML Team
Author-email: Flow ML Team <support@flowml.ai>
Maintainer-email: Flow ML Team <support@flowml.ai>
License: MIT
Project-URL: Homepage, https://github.com/flowml/flowprep-ml
Project-URL: Documentation, https://flowprep-ml.readthedocs.io/
Project-URL: Repository, https://github.com/flowml/flowprep-ml
Project-URL: Bug Tracker, https://github.com/flowml/flowprep-ml/issues
Keywords: machine learning,data preprocessing,pandas,scikit-learn,data science,ml
Classifier: Development Status :: 5 - Production/Stable
Classifier: Intended Audience :: Developers
Classifier: Intended Audience :: Science/Research
Classifier: License :: OSI Approved :: MIT License
Classifier: Operating System :: OS Independent
Classifier: Programming Language :: Python :: 3
Classifier: Programming Language :: Python :: 3.8
Classifier: Programming Language :: Python :: 3.9
Classifier: Programming Language :: Python :: 3.10
Classifier: Programming Language :: Python :: 3.11
Classifier: Programming Language :: Python :: 3.12
Classifier: Topic :: Scientific/Engineering :: Artificial Intelligence
Classifier: Topic :: Scientific/Engineering :: Information Analysis
Classifier: Topic :: Software Development :: Libraries :: Python Modules
Requires-Python: >=3.8
License-File: LICENSE
Requires-Dist: pandas>=1.3.0
Requires-Dist: numpy>=1.21.0
Requires-Dist: scikit-learn>=1.0.0
Requires-Dist: openpyxl>=3.0.0
Requires-Dist: xlrd>=2.0.0
Provides-Extra: dev
Requires-Dist: pytest>=6.0; extra == "dev"
Requires-Dist: pytest-cov>=2.0; extra == "dev"
Requires-Dist: black>=21.0; extra == "dev"
Requires-Dist: flake8>=3.8; extra == "dev"
Requires-Dist: mypy>=0.800; extra == "dev"
Requires-Dist: jupyter>=1.0; extra == "dev"
Provides-Extra: docs
Requires-Dist: sphinx>=4.0; extra == "docs"
Requires-Dist: sphinx-rtd-theme>=0.5; extra == "docs"
Requires-Dist: myst-parser>=0.15; extra == "docs"
Dynamic: author
Dynamic: home-page
Dynamic: license-file
Dynamic: requires-python
